MANIFEST.in
README.rst
setup.cfg
setup.py
masheryapi/__init__.py
masheryapi.egg-info/PKG-INFO
masheryapi.egg-info/SOURCES.txt
masheryapi.egg-info/dependency_links.txt
masheryapi.egg-info/entry_points.txt
masheryapi.egg-info/requires.txt
masheryapi.egg-info/top_level.txt
masheryapi/api/__init__.py
masheryapi/api/masheryV2.py
masheryapi/api/masheryV3.py
masheryapi/scripts/__init__.py
masheryapi/scripts/import_external_api_definitions.py
masheryapi/services/__init__.py
masheryapi/services/v3/__init__.py
masheryapi/services/v3/apis.py
masheryapi/services/v3/auth.py
masheryapi/services/v3/base.py